semver_git_hook/__init__.py
semver_git_hook-1.0.5.dist-info/LICENSE
semver_git_hook-1.0.5.dist-info/METADATA
semver_git_hook-1.0.5.dist-info/WHEEL
semver_git_hook-1.0.5.dist-info/entry_points.txt
semver_git_hook-1.0.5.dist-info/top_level.txt
semver_git_hook-1.0.5.dist-info/RECORD
