Metadata-Version: 2.1
Name: semver-git-hook
Version: 1.0.5
Summary: Enforce semver management in git repositories
Home-page: http://github.com/eregnier/semver-git-hook
Author: Eric Régnier
Author-email: utopman@gmail.com
License: MIT
Keywords: utility,productivity,tool,versionning,git,semver
Platform: UNKNOWN
Classifier: Programming Language :: Python
Classifier: Programming Language :: Python :: 3
Classifier: Programming Language :: Python :: 3.6
Classifier: Programming Language :: Python :: 3.7
Classifier: Programming Language :: Python :: Implementation :: PyPy
Classifier: Programming Language :: Python :: Implementation :: Jython
Classifier: Intended Audience :: Developers
Requires-Dist: pick
Requires-Dist: termcolor
